MANIFEST.in
README.rst
setup.cfg
setup.py
docs/HISTORY.txt
docs/INSTALL.txt
docs/LICENSE.GPL
docs/LICENSE.txt
medialog/.DS_Store
medialog/__init__.py
medialog/__init__.pyc
medialog.imageexport.egg-info/PKG-INFO
medialog.imageexport.egg-info/SOURCES.txt
medialog.imageexport.egg-info/dependency_links.txt
medialog.imageexport.egg-info/entry_points.txt
medialog.imageexport.egg-info/namespace_packages.txt
medialog.imageexport.egg-info/not-zip-safe
medialog.imageexport.egg-info/requires.txt
medialog.imageexport.egg-info/top_level.txt
medialog/imageexport/.DS_Store
medialog/imageexport/__init__.py
medialog/imageexport/__init__.pyc
medialog/imageexport/configure.zcml
medialog/imageexport/vocabulary.py
medialog/imageexport/browser/.DS_Store
medialog/imageexport/browser/__init__.py
medialog/imageexport/browser/__init__.pyc
medialog/imageexport/browser/configure.zcml
medialog/imageexport/browser/csvexport.py
medialog/imageexport/browser/dimageexport.py
medialog/imageexport/browser/dimageexport.pyc
medialog/imageexport/browser/imageexport.pt
medialog/imageexport/browser/imageexport.py
medialog/imageexport/browser/imageexport.pyc
medialog/imageexport/browser/listexport.py
medialog/imageexport/browser/testexport.py
medialog/imageexport/profiles/.DS_Store
medialog/imageexport/profiles/default/actions.xml
medialog/imageexport/profiles/default/metadata.xml