Metadata-Version: 1.0
Name: medialog.imageexport
Version: 0.5
Summary: Export Plone images pil scale imagescale
Home-page: http://www.medialog.no
Author: Espen Moe-Nilssen
Author-email: espen@medialog.no
License: GPL
Keywords: plone images preview export
Platform: UNKNOWN
Classifier: Environment :: Web Environment
Classifier: Development Status :: 4 - Beta
Classifier: Framework :: Plone
Classifier: Framework :: Plone :: 4.1
Classifier: Framework :: Plone :: 4.2
Classifier: Framework :: Plone :: 4.3
Classifier: Framework :: Plone :: 5.0
Classifier: Framework :: Zope2
Classifier: Framework :: Zope3
Classifier: Intended Audience :: Developers
Classifier: Intended Audience :: End Users/Desktop
Classifier: Operating System :: OS Independent
Classifier: Programming Language :: Python
Classifier: Programming Language :: Python :: 2.6
Classifier: Programming Language :: Python :: 2.7
Classifier: Topic :: Internet
Classifier: Topic :: Software Development :: Libraries :: Python Modules
